straycat/__init__.py
straycat/text_preprocessing/__init__.py
straycat/text_preprocessing/core_text_preprocessing.py
straycat/text_preprocessing/count_decorator.py
straycat/text_preprocessing/text_preprocessing.py
straycat-1.0.0.dist-info/AUTHORS.rst
straycat-1.0.0.dist-info/LICENSE
straycat-1.0.0.dist-info/METADATA
straycat-1.0.0.dist-info/WHEEL
straycat-1.0.0.dist-info/top_level.txt
straycat-1.0.0.dist-info/RECORD
