Metadata-Version: 2.1
Name: straycat
Version: 1.0.0
Summary: Easy NLP implementation for Indonesian Language
Home-page: https://github.com/hradkafeira/straycat
Author: Arief Akbar Hidayat
Author-email: hidayat.ariefakbar@gmail.com
License: MIT license
Keywords: straycat
Platform: UNKNOWN
Classifier: Development Status :: 2 - Pre-Alpha
Classifier: Intended Audience :: Developers
Classifier: License :: OSI Approved :: MIT License
Classifier: Natural Language :: English
Classifier: Programming Language :: Python :: 3
Classifier: Programming Language :: Python :: 3.6
Classifier: Programming Language :: Python :: 3.7
Classifier: Programming Language :: Python :: 3.8
Classifier: Programming Language :: Python :: 3.9
Classifier: Programming Language :: Python :: 3.10
Classifier: Programming Language :: Python :: 3.11
Requires-Python: >=3.6
Requires-Dist: Sastrawi (>=1.0.1)
Requires-Dist: nltk (>=3.6.5)
Requires-Dist: pandas
Requires-Dist: spacy (>=3.3.1)
